AUTHORS
INSTALL
LICENSE
MANIFEST.in
README.rst
setup.py
django_rflatpages.egg-info/PKG-INFO
django_rflatpages.egg-info/SOURCES.txt
django_rflatpages.egg-info/dependency_links.txt
django_rflatpages.egg-info/not-zip-safe
django_rflatpages.egg-info/requires.txt
django_rflatpages.egg-info/top_level.txt
docs/Makefile
docs/source/conf.py
docs/source/index.rst
rflatpages/__init__.py
rflatpages/admin.py
rflatpages/forms.py
rflatpages/models.py
rflatpages/tests.py
rflatpages/urls.py
rflatpages/views.py
rflatpages/migrations/0001_initial.py
rflatpages/migrations/0002_auto__del_field_pages_template.py
rflatpages/migrations/0003_auto__add_field_pages_template.py
rflatpages/migrations/__init__.py
rflatpages/rflatpages-example/manage.py
rflatpages/rflatpages-example/project/__init__.py
rflatpages/rflatpages-example/project/context_processors.py
rflatpages/rflatpages-example/project/settings.py
rflatpages/rflatpages-example/project/urls.py
rflatpages/rflatpages-example/project/wsgi.py
rflatpages/rflatpages-example/project/db/delete.me
rflatpages/rflatpages-example/project/media/uploads/delete.me
rflatpages/rflatpages-example/project/static/css/PIE.htc
rflatpages/rflatpages-example/project/static/css/bootstrap-responsive.css
rflatpages/rflatpages-example/project/static/css/bootstrap-responsive.min.css
rflatpages/rflatpages-example/project/static/css/bootstrap.css
rflatpages/rflatpages-example/project/static/css/bootstrap.min.css
rflatpages/rflatpages-example/project/static/css/colorbox.css
rflatpages/rflatpages-example/project/static/css/custom.css
rflatpages/rflatpages-example/project/static/css/fonts/Calluna-Regular.otf
rflatpages/rflatpages-example/project/static/filebrowser/css/filebrowser.css
rflatpages/rflatpages-example/project/static/filebrowser/css/filebrowser.css.rej
rflatpages/rflatpages-example/project/static/filebrowser/img/filebrowser_icon_delete.gif
rflatpages/rflatpages-example/project/static/filebrowser/img/filebrowser_icon_delete_hover.gif
rflatpages/rflatpages-example/project/static/filebrowser/img/filebrowser_icon_rename.gif
rflatpages/rflatpages-example/project/static/filebrowser/img/filebrowser_icon_rename_hover.gif
