Metadata-Version: 1.0
Name: django-rflatpages
Version: 0.0.6
Summary: Yet another Django Flatpages App
Home-page: http://bitbucket.org/r0sk/django-rflatpages
Author: Oscar M. Lage Guitian
Author-email: r0sk10@gmail.com
License: BSD licence, see LICENSE file
Keywords: django application flatpages
Platform: UNKNOWN
Classifier: Development Status :: 4 - Beta
Classifier: Environment :: Web Environment
Classifier: Framework :: Django
Classifier: Intended Audience :: Developers
Classifier: License :: OSI Approved :: BSD License
Classifier: Operating System :: OS Independent
Classifier: Programming Language :: Python
Classifier: Topic :: Internet :: WWW/HTTP :: Dynamic Content
Classifier: Topic :: Software Development :: Libraries :: Python Modules
